Project4bim/autoencoder.py
Project4bim/module0.py
Project4bim/test.py
Project4bim/utils.py
Project4bim/model_vae/decoder/checkpoint
Project4bim/model_vae/decoder/saved_decoder.data-00000-of-00001
Project4bim/model_vae/decoder/saved_decoder.index
Project4bim/model_vae/encoder/checkpoint
Project4bim/model_vae/encoder/saved_encoder.data-00000-of-00001
Project4bim/model_vae/encoder/saved_encoder.index
example4bim2-1.0.0.dist-info/LICENSE
example4bim2-1.0.0.dist-info/METADATA
example4bim2-1.0.0.dist-info/WHEEL
example4bim2-1.0.0.dist-info/top_level.txt
example4bim2-1.0.0.dist-info/RECORD
