Metadata-Version: 2.1
Name: example4bim2
Version: 1.0.0
Summary: A example package
Home-page: https://github.com/ruthh1/Projet-4bim
Author: Team2
Author-email: seungyun.shin@insa-lyon.fr
License: UNKNOWN
Platform: UNKNOWN
Classifier: Programming Language :: Python :: 3
Classifier: License :: OSI Approved :: MIT License
Classifier: Operating System :: OS Independent
Requires-Python: >=3.6
License-File: LICENSE
